biaplotter/__init__.py
biaplotter/_version.py
biaplotter/artists.py
biaplotter/artists_base.py
biaplotter/colormap.py
biaplotter/napari.yaml
biaplotter/plotter.py
biaplotter/selectors.py
biaplotter/_tests/__init__.py
biaplotter/_tests/test_artists.py
biaplotter/_tests/test_selectors.py
biaplotter/_tests/test_widget.py
biaplotter/icons/button1.png
biaplotter/icons/button1_checked.png
biaplotter/icons/ellipse.png
biaplotter/icons/ellipse_checked.png
biaplotter/icons/lasso.png
biaplotter/icons/lasso_checked.png
biaplotter/icons/rectangle.png
biaplotter/icons/rectangle_checked.png
biaplotter/icons/show_overlay.png
biaplotter/icons/show_overlay_checked.png
biaplotter-0.4.2.dist-info/licenses/LICENSE
biaplotter-0.4.2.dist-info/METADATA
biaplotter-0.4.2.dist-info/WHEEL
biaplotter-0.4.2.dist-info/entry_points.txt
biaplotter-0.4.2.dist-info/top_level.txt
biaplotter-0.4.2.dist-info/RECORD
