Metadata-Version: 2.4
Name: biaplotter
Version: 0.4.2
Summary: A base napari plotter widget for interactive plotting
Author-email: Marcelo Leomil Zoccoler <marzoccoler@gmail.com>
License: 
Project-URL: Homepage, https://github.com/BiAPoL/biaplotter
Project-URL: Bug Tracker, https://github.com/BiAPoL/biaplotter/issues
Project-URL: Documentation, https://biapol-biaplotter.readthedocs.io/en/stable/
Project-URL: Source Code, https://github.com/BiAPoL/biaplotter
Project-URL: User Support, https://github.com/BiAPoL/biaplotter/issues
Classifier: Development Status :: 2 - Pre-Alpha
Classifier: Framework :: napari
Classifier: Intended Audience :: Developers
Classifier: License :: OSI Approved :: BSD License
Classifier: Operating System :: OS Independent
Classifier: Programming Language :: Python
Classifier: Programming Language :: Python :: 3
Classifier: Programming Language :: Python :: 3 :: Only
Classifier: Programming Language :: Python :: 3.10
Classifier: Programming Language :: Python :: 3.11
Classifier: Programming Language :: Python :: 3.12
Classifier: Programming Language :: Python :: 3.13
Classifier: Topic :: Scientific/Engineering :: Image Processing
Classifier: Topic :: Scientific/Engineering :: Visualization
Requires-Python: >=3.10
License-File: LICENSE
Requires-Dist: numpy>=1.22.0
Requires-Dist: magicgui
Requires-Dist: qtpy
Requires-Dist: napari-matplotlib
Requires-Dist: nap-plot-tools>=0.1.0
Provides-Extra: testing
Requires-Dist: tox; extra == "testing"
Requires-Dist: pytest; extra == "testing"
Requires-Dist: pytest-cov; extra == "testing"
Requires-Dist: pytest-qt; extra == "testing"
Requires-Dist: napari; extra == "testing"
Requires-Dist: pyqt5; extra == "testing"
Dynamic: license-file
